{
  "url": "https://month-opportunity-displaying-shine.trycloudflare.com",
  "updated_at": "2026-07-05T09:59:48+10:00",
  "urls": [
    {
      "url": "https://month-opportunity-displaying-shine.trycloudflare.com",
      "updated_at": "2026-07-05T09:59:48+10:00"
    },
    {
      "url": "https://provision-examinations-suse-robinson.trycloudflare.com",
      "updated_at": "2026-07-05T09:29:30+10:00"
    },
    {
      "url": "https://logging-dependent-john-stayed.trycloudflare.com",
      "updated_at": "2026-07-05T08:59:15+10:00"
    },
    {
      "url": "https://shade-phil-strategies-regarding.trycloudflare.com",
      "updated_at": "2026-07-05T08:28:58+10:00"
    },
    {
      "url": "https://authentic-run-definition-preceding.trycloudflare.com",
      "updated_at": "2026-07-05T07:58:42+10:00"
    }
  ]
}
