{
  "url": "https://functional-consultancy-prefer-specially.trycloudflare.com",
  "updated_at": "2026-07-07T05:19:37+10:00",
  "urls": [
    {
      "url": "https://functional-consultancy-prefer-specially.trycloudflare.com",
      "updated_at": "2026-07-07T05:19:37+10:00"
    },
    {
      "url": "https://collaborative-richard-passage-angle.trycloudflare.com",
      "updated_at": "2026-07-07T04:49:33+10:00"
    },
    {
      "url": "https://bishop-helena-golf-text.trycloudflare.com",
      "updated_at": "2026-07-07T04:49:11+10:00"
    },
    {
      "url": "https://specialists-relevance-inbox-edge.trycloudflare.com",
      "updated_at": "2026-07-07T04:19:06+10:00"
    },
    {
      "url": "https://tomato-browsing-cir-tiffany.trycloudflare.com",
      "updated_at": "2026-07-07T03:48:44+10:00"
    }
  ]
}
