{
  "url": "https://flour-nice-ensuring-pensions.trycloudflare.com",
  "updated_at": "2026-07-11T20:10:59+10:00",
  "urls": [
    {
      "url": "https://flour-nice-ensuring-pensions.trycloudflare.com",
      "updated_at": "2026-07-11T20:10:59+10:00"
    },
    {
      "url": "https://driven-timeline-drain-filling.trycloudflare.com",
      "updated_at": "2026-07-11T19:40:48+10:00"
    },
    {
      "url": "https://reserve-secondary-sign-rat.trycloudflare.com",
      "updated_at": "2026-07-11T19:10:16+10:00"
    },
    {
      "url": "https://apparel-quite-medication-major.trycloudflare.com",
      "updated_at": "2026-07-11T18:39:49+10:00"
    },
    {
      "url": "https://standing-living-cio-productivity.trycloudflare.com",
      "updated_at": "2026-07-11T18:09:32+10:00"
    }
  ]
}
