{
  "url": "https://markers-derived-rfc-figures.trycloudflare.com",
  "updated_at": "2026-07-13T06:13:44+10:00",
  "urls": [
    {
      "url": "https://markers-derived-rfc-figures.trycloudflare.com",
      "updated_at": "2026-07-13T06:13:44+10:00"
    },
    {
      "url": "https://concentrate-societies-rouge-florence.trycloudflare.com",
      "updated_at": "2026-07-13T06:13:23+10:00"
    },
    {
      "url": "https://feature-log-garden-palace.trycloudflare.com",
      "updated_at": "2026-07-13T05:43:17+10:00"
    },
    {
      "url": "https://shepherd-laid-perception-listprice.trycloudflare.com",
      "updated_at": "2026-07-13T05:42:46+10:00"
    },
    {
      "url": "https://responded-tex-modem-bag.trycloudflare.com",
      "updated_at": "2026-07-13T05:42:29+10:00"
    }
  ]
}
