{
  "url": "https://creating-ips-finals-expenditure.trycloudflare.com",
  "updated_at": "2026-07-19T07:56:24+10:00",
  "urls": [
    {
      "url": "https://creating-ips-finals-expenditure.trycloudflare.com",
      "updated_at": "2026-07-19T07:56:24+10:00"
    },
    {
      "url": "https://diagram-unlikely-critical-ease.trycloudflare.com",
      "updated_at": "2026-07-19T07:56:14+10:00"
    },
    {
      "url": "https://bronze-poultry-descriptions-envelope.trycloudflare.com",
      "updated_at": "2026-07-19T07:56:04+10:00"
    },
    {
      "url": "https://ray-guild-provides-skill.trycloudflare.com",
      "updated_at": "2026-07-19T07:55:53+10:00"
    },
    {
      "url": "https://somewhat-streaming-coding-genes.trycloudflare.com",
      "updated_at": "2026-07-19T07:25:52+10:00"
    }
  ]
}
