{
  "url": "https://hourly-checks-marijuana-met.trycloudflare.com",
  "updated_at": "2026-07-09T07:15:26+10:00",
  "urls": [
    {
      "url": "https://hourly-checks-marijuana-met.trycloudflare.com",
      "updated_at": "2026-07-09T07:15:26+10:00"
    },
    {
      "url": "https://peak-subscriber-great-pamela.trycloudflare.com",
      "updated_at": "2026-07-09T07:14:46+10:00"
    },
    {
      "url": "https://boc-resume-sub-raises.trycloudflare.com",
      "updated_at": "2026-07-09T07:14:27+10:00"
    },
    {
      "url": "https://five-signal-aviation-endangered.trycloudflare.com",
      "updated_at": "2026-07-09T07:13:48+10:00"
    },
    {
      "url": "https://asbestos-ftp-yield-dim.trycloudflare.com",
      "updated_at": "2026-07-09T06:43:27+10:00"
    }
  ]
}
