{
  "url": "https://instruments-newark-greatly-extension.trycloudflare.com",
  "updated_at": "2026-07-20T12:19:02+10:00",
  "urls": [
    {
      "url": "https://instruments-newark-greatly-extension.trycloudflare.com",
      "updated_at": "2026-07-20T12:19:02+10:00"
    },
    {
      "url": "https://chances-confident-additional-patches.trycloudflare.com",
      "updated_at": "2026-07-20T12:18:41+10:00"
    },
    {
      "url": "https://number-concentration-speak-web.trycloudflare.com",
      "updated_at": "2026-07-20T12:18:26+10:00"
    },
    {
      "url": "https://chips-radiation-anybody-prayer.trycloudflare.com",
      "updated_at": "2026-07-20T12:18:16+10:00"
    },
    {
      "url": "https://owen-effects-video-split.trycloudflare.com",
      "updated_at": "2026-07-20T11:48:08+10:00"
    }
  ]
}
