{
  "url": "https://age-persistent-singh-shake.trycloudflare.com",
  "updated_at": "2026-06-30T17:40:01+10:00",
  "urls": [
    {
      "url": "https://age-persistent-singh-shake.trycloudflare.com",
      "updated_at": "2026-06-30T17:40:01+10:00"
    },
    {
      "url": "https://rico-effective-van-breathing.trycloudflare.com",
      "updated_at": "2026-06-30T17:39:50+10:00"
    },
    {
      "url": "https://doom-bald-scsi-missions.trycloudflare.com",
      "updated_at": "2026-06-30T17:09:44+10:00"
    },
    {
      "url": "https://argument-legislative-bunch-vessel.trycloudflare.com",
      "updated_at": "2026-06-30T16:39:25+10:00"
    },
    {
      "url": "https://votes-branches-age-unsigned.trycloudflare.com",
      "updated_at": "2026-06-30T16:09:12+10:00"
    }
  ]
}
