{
  "url": "https://further-memory-reaction-attributes.trycloudflare.com",
  "updated_at": "2026-07-04T15:15:28+10:00",
  "urls": [
    {
      "url": "https://further-memory-reaction-attributes.trycloudflare.com",
      "updated_at": "2026-07-04T15:15:28+10:00"
    },
    {
      "url": "https://exterior-oclc-correspondence-comfortable.trycloudflare.com",
      "updated_at": "2026-07-04T14:45:16+10:00"
    },
    {
      "url": "https://indices-where-timing-marketing.trycloudflare.com",
      "updated_at": "2026-07-04T14:30:12+10:00"
    },
    {
      "url": "https://lifetime-diameter-worldwide-successfully.trycloudflare.com",
      "updated_at": "2026-07-04T13:44:39+10:00"
    },
    {
      "url": "https://internal-foto-fotos-got.trycloudflare.com",
      "updated_at": "2026-07-04T13:14:27+10:00"
    }
  ]
}
